frformat/__init__.py
frformat/code_rna.py
frformat/common.py
frformat/custom_format.py
frformat/enum_format.py
frformat/formatter.py
frformat/geo/canton.py
frformat/geo/canton_frozenset.py
frformat/geo/code_commune_insee.py
frformat/geo/code_commune_insee_frozenset.py
frformat/geo/code_fantoir.py
frformat/geo/code_fantoir_frozenset.py
frformat/geo/code_pays.py
frformat/geo/code_pays_frozenset.py
frformat/geo/code_postal.py
frformat/geo/code_postal_frozenset.py
frformat/geo/code_region.py
frformat/geo/commune.py
frformat/geo/commune_frozenset.py
frformat/geo/coordonnees_gps_francaises.py
frformat/geo/departement.py
frformat/geo/departement_frozenset.py
frformat/geo/latitude_l93.py
frformat/geo/longitude_l93.py
frformat/geo/numero_departement.py
frformat/geo/pays.py
frformat/geo/pays_frozenset.py
frformat/geo/region.py
frformat/geo/region_frozenset.py
frformat/geo_format.py
frformat/nomenclature_acte_format.py
frformat/options.py
frformat/siren.py
frformat/siret.py
frformat/versioned_set.py
frformat-0.4.1.dist-info/LICENSE
frformat-0.4.1.dist-info/METADATA
frformat-0.4.1.dist-info/WHEEL
frformat-0.4.1.dist-info/RECORD
