Metadata-Version: 2.3
Name: frformat
Version: 0.4.1
Summary: 
License: AGPL-3.0
Author: Pierre Camilleri
Author-email: 22995923+pierrecamilleri@users.noreply.github.com
Requires-Python: >=3.9,<4.0
Classifier: License :: OSI Approved :: GNU Affero General Public License v3
Classifier: Programming Language :: Python :: 3
Classifier: Programming Language :: Python :: 3.9
Classifier: Programming Language :: Python :: 3.10
Classifier: Programming Language :: Python :: 3.11
Classifier: Programming Language :: Python :: 3.12
Classifier: Programming Language :: Python :: 3.13
Requires-Dist: python-stdnum (>=1.19,<2.0)
Requires-Dist: shapely (>=2.0.2,<3.0.0)
